[
  {
    "type": "airfield",
    "name": "EBBL",
    "location": [51.167667, 5.468667]
  },
  {
    "type": "racetrack3",
    "name": "EBBL CTR",
    "centers": [[51.074167, 5.3045],[51.236833, 5.608333]],
    "radius": 5,
    "altitude": [0,2500],
    "color": "purple"
  },
  {
    "type": "airfield",
    "name": "EBBE",
    "location": [50.754667, 4.766833]
  },
  {
    "type": "airspace",
    "name": "EBBE CTR",
    "color": "purple",
    "altitude": [0,2500],
    "points": [
      [50.691833, 4.502667],
      [50.953, 4.866833],
      [50.892667, 5.04],
      [50.806, 5.154167],
      [50.692833, 4.920833],
      [50.656833, 4.825833],
      [50.583667, 4.708],
      [50.691933, 4.502667]
    ]
  },
  {
    "type": "airfield",
    "name": "EBST",
    "location": [50.7885, 5.201]
  },
  {
    "type": "airfield",
    "name": "EBTN",
    "location": [50.775667, 4.954667]
  },
  {
    "type": "airfield",
    "name": "EBBX",
    "location": [49.888333, 5.221]
  },
  {
    "type": "airfield",
    "name": "EBWE",
    "location": [51.389833, 4.9555]
  },
  {
    "type": "airfield",
    "name": "EBSL",
    "location": [50.941833, 5.587667]
  },
  {
    "type": "airfield",
    "name": "EBLG",
    "location": [50.635167, 5.439]
  },
  {
    "type": "racetrack3",
    "name": "EBLG CTR",
    "centers": [[50.6895, 5.534167],[50.5745, 5.351667]],
    "radius": 5,
    "altitude": [0,2500],
    "color": "purple"
  },
  {
    "type": "airfield",
    "name": "EHDL",
    "location": [52.059728, 5.871936]
  },
  {
    "type": "airfield",
    "name": "EHDP",
    "location": [51.517033, 5.853383]
  },
  {
    "type": "airfield",
    "name": "EHEH",
    "location": [51.450133, 5.374514]
  },
  {
    "type": "racetrack3",
    "name": "EHEH/EHVK CTR",
    "centers": [[51.45, 5.371333],[51.657208, 5.707825]],
    "radius": 8,
    "altitude": [0,3000],
    "color": "purple"
  },
  {
    "type": "airfield",
    "name": "EHGR",
    "location": [51.567378, 4.931836]
  },
  {
    "type": "airfield",
    "name": "EHVK",
    "location": [51.657208, 5.707825]
  },
  {
    "type": "airfield",
    "name": "EHSB",
    "location": [52.134041, 5.265498]
  },
  {
    "type": "airfield",
    "name": "EHTW",
    "location": [52.272167, 6.886833]
  }
]
